README
setup.py
test/test_challenger.py
test/test_compile.py
tiddlywebplugins/__init__.py
tiddlywebplugins/ldapauth.py
tiddlywebplugins.ldapauth.egg-info/PKG-INFO
tiddlywebplugins.ldapauth.egg-info/SOURCES.txt
tiddlywebplugins.ldapauth.egg-info/dependency_links.txt
tiddlywebplugins.ldapauth.egg-info/namespace_packages.txt
tiddlywebplugins.ldapauth.egg-info/not-zip-safe
tiddlywebplugins.ldapauth.egg-info/requires.txt
tiddlywebplugins.ldapauth.egg-info/top_level.txt