Metadata-Version: 1.0
Name: tiddlywebplugins.ldapauth
Version: 0.1.1
Summary: Allows TiddlyWeb users to Authenticate against an LDAP server.
Home-page: http://pypi.python.org/pypi/tiddlywebplugins.ldapauth
Author: Ben Paddock
Author-email: pads@thisispads.me.uk
License: UNKNOWN
Platform: Posix; MacOS X; Windows
